{
  "30a_music": {
    "name": "30A Music",
    "url": "https://30a-tv.com/music.m3u8",
    "group-title": "Music"
  },
  "abc_news": {
    "name": "ABC News Live",
    "url": "https://abcnews.go.com/Live",
    "group-title": "News"
  },
  "afro-beats": {
    "name": "Afro Beats",
    "url": "https://stream.ecable.tv/afrobeats/index.m3u8",
    "group-title": "Music"
  },
  "akilikids": {
    "name": "Akili Kids! TV",
    "url": "https://akilikids.co.ke/live/",
    "group-title": "Kids"
  },
  "al-jazeera-english": {
    "name": "Al Jazeera English",
    "url": "https://live-hls-apps-aje-v3-fa.getaj.net/AJE/index.m3u8",
    "logo": "https://i.imgur.com/7bRVpnu.png",
    "group-title": "Entertainmentl"
  },
  "al_jazeera": {
    "name": "Al Jazeera English",
    "url": "https://www.aljazeera.com/live",
    "logo": "https://i.imgur.com/7bRVpnu.png",
    "group-title": "Entertainment"
  },
  "animax": {
    "name": "Animax",
    "url": "https://amg02159-kcglobal-amg02159c1-samsung-in-521.playouts.now.amagi.tv/playlist/amg02159-kcglobal-animax-samsungin/playlist.m3u8",
    "group-title": "Kids"
  },
  "baby_first": {
    "name": "Baby First TV",
    "url": "https://streams2.sofast.tv/v1/master/611d79b11b77e2f571934fd80ca1413453772ac7/c8d16110-566c-4e95-a1df-55d175e9e201/manifest.m3u8",
    "group-title": "Kids"
  },
  "baby_shark": {
    "name": "Baby Shark Kids",
    "url": "https://newidco-babysharktv-1-eu.rakuten.wurl.tv/playlist.m3u8",
    "group-title": "Kids"
  },
  "b3_music": {
    "name": "B3 Music",
    "url": "https://live20.bozztv.com/akamaissh101/ssh101/d3tvnet/playlist.m3u8",
    "group-title": "Music"
  },
  "bbc_doctor_who": {
    "name": "BBC Doctor Who",
    "url": "https://amg00793-amg00793c15-rakuten-es-5359.playouts.now.amagi.tv/playlist.m3u8",
    "group-title": "General"
  },
  "bein_sports": {
    "name": "beIN SPORTS",
    "url": "https://aegis-cloudfront-1.tubi.video/82c7f2de-f4ea-44a4-8200-069c5c0bb639/playlist.m3u8",
    "logo": "https://i.imgur.com/QWo0x7S.jpg",
    "group-title": "Sports"
  },
  "bet_her": {
    "name": "BET her",
    "url": "https://fl3.moveonjoy.com/BET_HER/index.m3u8",
    "group-title": "Entertainment"
  },
  "biz_tv": {
    "name": "Biz Tv",
    "url": "https://thegateway.app/BizAndYou/BizTV/playlist.m3u8",
    "group-title": "Entertainment"
  },
  "bloomberg_tv_us": {
    "name": "Bloomberg TV US",
    "url": "https://bloomberg-bloomberg-3-br.samsung.wurl.tv/manifest/playlist.m3u8",
    "group-title": "News"
  },
  "boomerang": {
    "name": "Boomerang",
    "url": "https://dai.google.com/linear/hls/event/d4J7lXUyQp2dZQ-pXJ-ItA/master.m3u8",
    "group-title": "News"
  },
  "bollywood_classic": {
    "name": "Bollywood Classic",
    "url": "https://d35j504z0x2vu2.cloudfront.net/v1/master/0bc8e8376bd8417a1b6761138aa41c26c7309312/bollywood-classic/manifest.m3u8",
    "logo": "https://i.ibb.co/WzLwj3X/IMG-20230703-155036.jpg",
    "group-title": "Movies"
  },
  "bollywood_hd": {
    "name": "Bollywood HD",
    "url": "https://d35j504z0x2vu2.cloudfront.net/v1/master/0bc8e8376bd8417a1b6761138aa41c26c7309312/bollywood-hd/manifest.m3u8",
    "logo": "https://i.ibb.co/WzLwj3X/IMG-20230703-155036.jpg",
    "group-title": "Movies"
  },
  "btn": {
    "name": "BTN",
    "url": "https://2-fss-2.streamhoster.com/pl_138/205510-3094608-1/playlist.m3u8",
    "group-title": "General"
  },
  "cbeebies": {
    "name": "CBeebies Kids",
    "url": "https://vs-hls-pushb-uk-live.akamaized.net/x=3/i=urn:bbc:pips:service:cbeebies_hd/t=3840/v=pv14/b=5080016/main.m3u8",
    "group-title": "Kids"
  },
  "chinola": {
    "name": "CHINOLA TV",
    "url": "https://tv.wracanal10.com:3300/live/chinolatvlive.m3u8",
    "group-title": "Kids"
  },
  "citizen-tv": {
    "name": "Citizen TV",
    "url": "https://www.youtube.com/embed/live_stream?channel=UChBQgieUidXV1CmDxSdRm3g&controls=0&modestbranding=1&rel=0&fs=1&disablekb=1&iv_load_policy=3",
    "logo": "https://viewtv-p2s3.onrender.com/uploads/citizen.png",
    "group-title": "News"
  },
  "citizen-tv-extra": {
    "name": "Citizen Extra",
    "url": "https://www.youtube.com/embed/MDA0XHrnNl4",
    "logo": "https://viewtv-p2s3.onrender.com/uploads/citizen.png",
    "group-title": "News"
  },
  "classic_movie": {
    "name": "Classic Movie",
    "url": "https://30a-tv.com/feeds/pzaz/30atvmovies.m3u8",
    "group-title": "Movies"
  },
  "clan_hevc": {
    "name": "Clan HEVC",
    "url": "https://d3nnqrdb77sy13.cloudfront.net/v1/master/3722c60a815c199d9c0ef36c5b73da68a62b09d1/cc-eimbp20cszixb/Clan_ES.m3u8",
    "group-title": "General"
  },
  "cmt_east": {
    "name": "CMT East",
    "url": "https://fl3.moveonjoy.com/CMT/index.m3u8",
    "group-title": "General"
  },
  "dazn_combat": {
    "name": "Dazn Combat",
    "url": "https://dazn-combat-rakuten.amagi.tv/hls/amagi_hls_data_rakutenAA-dazn-combat-rakuten/CDN/master.m3u8",
    "group-title": "Sports"
  },
  "discovery_kids": {
    "name": "Discovery Kids (LATAM)",
    "url": "https://playout1753.livextend.tv/live/discoverykids_adaptive/index.m3u8",
    "group-title": "kids"
  },
  "disney": {
    "name": "Disney Kids",
    "url": "https://fl5.moveonjoy.com/DISNEY/index.m3u8",
    "group-title": "kids"
  },
  "disney-jr": {
    "name": "Disney JR",
    "url": "https://fl3.moveonjoy.com/DISNEY_JR/index.m3u8",
    "group-title": "kids"
  },
  "disney_junior": {
    "name": "Disney Junior",
    "url": "https://disneynow-lh.akamaihd.net/i/disneyjr_1@356032/master.m3u8",
    "group-title": "kids"
  },
  "emmanuel-tv": {
    "name": "Emmanuel Tv",
    "url": "https://live20.bozztv.com/dvrfl06/astv/astv-emmanuel/index.m3u8",
    "group-title": "Religious"
  },
  "entertainment_tonight": {
    "name": "Entertainment Tonight",
    "url": "https://cbsta49f-cbsta49f-ms.global.ssl.fastly.net/amagi7b98-AmagiMixible/master/amagi7b98-AmagiMixible.m3u8",
    "group-title": "Entertainment"
  },
  "espn_plus": {
    "name": "ESPN+",
    "url": "https://plus.espn.com/live",
    "group-title": "Sports"
  },
  "fashion-find": {
    "name": "Fasion Find",
    "url": "https://qvc-amd-live.akamaized.net/hls/live/2034113/lsqvc5us/master.m3u8",
    "group-title": "Fashion"
  },
  "fite_wrestle": {
    "name": "FITE [wrestling]",
    "url": "https://d3d85c7qkywguj.cloudfront.net/scheduler/scheduleMaster/263.m3u8",
    "group-title": "Sports"
  },
  "france24-english": {
    "name": "France 24 English",
    "url": "https://live.france24.com/hls/live/2037218-b/F24_EN_HI_HLS/master_5000.m3u8",
    "group-title": "General"
  },
  "fox_soul": {
    "name": "Fox Soul",
    "url": "https://fl1.moveonjoy.com/FOX_SOUL/index.m3u8",
    "group-title": "General"
  },
  "fox23": {
    "name": "Fox23",
    "url": "https://live.field59.com/kbsi/kbsi1/playlist.m3u8",
    "group-title": "General"
  },
  "fuel-tv-sports": {
    "name": "Fuel Tv [sports]",
    "url": "https://amg01074-fueltv-fueltvemeaen-rakuten-b6j62.amagi.tv/hls/amagi_hls_data_rakutenAA-fueltvemeaen/CDN/master.m3u8",
    "group-title": "Sports"
  },
  "game-plus": {
    "name": "Game +",
    "url": "https://a-cdn.klowdtv.com/live2/fntsy_720p/playlist.m3u8",
    "group-title": "Sports"
  },
  "gem-drama": {
    "name": "Gem Drama",
    "url": "https://ca-rt.onetv.app/gemdrama/index-0.m3u8",
    "group-title": "Entertainment"
  },
  "gem-jr": {
    "name": "GEM JR",
    "url": "https://ca-rt.onetv.app/gemjunior/index-0.m3u8",
   "group-title": "Entertainment" 
  },
  "gem-kids": {
    "name": "GEM Kids",
    "url": "https://ca-rt.onetv.app/gemkids/index-0.m3u8",
    "group-title": "Entertainment"
  },
  "great-movies": {
    "name": "Great Movies",
    "url": "https://amg01753-narrativeuk-amg01753c3-lg-gb-1833.playouts.now.amagi.tv/playlist/amg01753-narrativeuk-greatmovies-lggb/playlist.m3u8",
    "group-title": "Movies"
  },
  "great-mystery": {
    "name": "Great Mystery",
    "url": "https://linear-861.frequency.stream/dist/lg-uk/861/hls/master/playlist.m3u8",
    "group-title": "Entertainment"
  },
  "hells-kitchen": {
    "name": "Hell's Kitchen",
    "url": "https://itv-hellskitchen-rakuten.amagi.tv/playlist.m3u8",
    "group-title": "Entertainment"
  },
  "hsn-east": {
    "name": "HSN East",
    "url": "https://qvc-amd-live.akamaized.net/hls/live/2034113/lshsn1uswest/master.m3u8",
    "group-title": "Entertainment"
  },
  "inooro-tv": {
    "name": "Inooro Tv",
    "url": "https://kenyalivetv.co.ke/tv/inooro-tv-live",
    "logo": "https://viewtv-p2s3.onrender.com/uploads/inooro.png",
    "group-title": "News"
  },
  "kameme-tv": {
    "name": "Kameme TV",
    "url": "https://kamemetv.co.ke/live/",
    "logo": "",
    "group-title": "News"
  },
  "kartoon_channel": {
    "name": "Kartoon Channel",
    "url": "https://cdn-apse1-prod.tsv2.amagi.tv/linear/amg01076-lightningintern-kartoonchannel-samsungnz/playlist.m3u8",
    "group-title": "Kids"
  },
  "kass-tv": {
    "name": "Kass TV",
    "url": "https://www.youtube.com/embed/4smx4SyYMbc",
    "logo": "https://viewtv-p2s3.onrender.com/uploads/kass.png",
    "group-title": "News"
  },
  "ketchap": {
    "name": "Ketchup",
    "url": "https://stream.ads.ottera.tv/playlist.m3u8?network_id=13171",
    "group-title": "Entertainment"
  },
  "kidsflix": {
    "name": "KidsFlix",
    "url": "https://stream-us-east-1.getpublica.com/playlist.m3u8?network_id=50",
    "group-title": "Kids"
  },
  "kiss-tv": {
    "name": "Kiss Tv",
    "url": "https://tv.broadcasting.ro/kisstv/a629c031-2170-4ee9-a36d-87a891aa3131.m3u8",
    "group-title": "Entertainment"
  },
  "k24-tv": {
    "name": "K24 TV",
    "url": "https://www.youtube.com/embed/_lB9oSok1FM?controls=1&modestbranding=1&rel=0&fs=1&disablekb=0&iv_load_policy=3",
    "logo": "https://viewtv-p2s3.onrender.com/uploads/K24.png",
    "group-title": "News"
  },
  "ktn": {
    "name": "KTN Home",
    "url": "https://www.youtube.com/embed/live_stream?channel=UCKVsdeoHExltrWMuK0hOWmg&controls=0&modestbranding=1&rel=0&fs=1&disablekb=1&iv_load_policy=3",
    "logo": "https://viewtv-p2s3.onrender.com/uploads/ktn.png",
    "group-title": "News"
  },
  "kbc": {
    "name": "KBC channel 1",
    "url": "https://kenyalivetv.co.ke/embed/kbc-channel-1-live",
    "logo": "https://kbc.co.ke/wp-content/uploads/2024/11/KBC-LOGO.png",
    "group-title": "News"
  },
  "life_end_time": {
    "name": "Life! End Time",
    "url": "https://2-fss-1.streamhoster.com/pl_122/200226-1427780-1/playlist.m3u8",
    "group-title": "Entertainment"
  },
  "lol_network": {
    "name": "LOL! Network",
    "url": "https://lol-lolnetwork-2-nl.samsung.wurl.tv/playlist.m3u8",
    "group-title": "Entertainment"
  },
  "military_history": {
    "name": "Military History",
    "url": "https://fl3.moveonjoy.com/Military_History/index.m3u8",
    "group-title": "Entertainment"
  },
  "movie-box": {
    "name": "Movie Box",
    "url": "https://cdn3.skygo.mn/live/disk1/Moviebox/HLS-FTA/Moviebox.m3u8",
    "group-title": "Movies"
  },
  "movies-bang": {
    "name": "Movies! ",
    "url": "https://dvrfl03.bozztv.com/hdirect/hdirect-ovair1-movies!/index.m3u8",
    "group-title": "Movies"
  },
  "pltv-usa-movies": {
    "name": "Movies HD",
    "url": "https://i.mjh.nz/PlutoTV/us.m3u8",
    "group-title": "Movies"
  },
  "moviesphere-hd": {
    "name": "MovieSphere HD",
    "url": "https://moviesphereuk-samsunguk.amagi.tv/playlist.m3u8",
    "group-title": "Movies"
  },
  "nbc-sports": {
    "name": "NBC Sports",
    "url": "https://www.nbcsports.com/live",
    "group-title": "Sports"
  },
  "nick-jr-east": {
    "name": "Nick Jr.",
    "url": "https://fl3.moveonjoy.com/NICK_JR/index.m3u8",
    "group-title": "Kids"
  },
  "nickelodeon": {
    "name": "Nickelodeon",
    "url": "https://nickelodeon-rakuten.amagi.tv/playlist.m3u8",
    "group-title": "Kids"
  },
  "ninja-kidz-tv": {
    "name": "Ninja Kidz TV",
    "url": "https://playworksdigital-ninjakidztv-1-us.xumo.wurl.tv/playlist.m3u8",
    "group-title": "Kids"
  },
  "ntv": {
    "name": "NTV Digital",
    "url": "https://ntvkenya.co.ke/live/",
    "logo": "https://viewtv-p2s3.onrender.com/uploads/ntv.png",
    "group-title": "News"
  },
  "ntv-kenya": {
    "name": "NTV",
    "url": "https://www.youtube.com/embed/p4BWnK2xeHw",
    "logo": "https://viewtv-p2s3.onrender.com/uploads/ntv.png",
    "group-title": "News"
  },
  "outdoor_channel": {
    "name": "Outdoor Channel",
    "url": "https://cdn-apse1-prod.tsv2.amagi.tv/linear/amg00718-outdoorchannela-outdoortvnz-samsungnz/playlist.m3u8",
    "group-title": "Travel"
  },
  "pbs_kids": {
    "name": "PBS Kids",
    "url": "https://kidslive-aka.amagi.tv/playlist.m3u8",
    "group-title": "Kids"
  },
  "pbs_kids_1": {
    "name": "PBS Kids 1",
    "url": "https://livestream.pbskids.org/out/v1/1e3d77b418ad4a819b3f4c80ac0373b5/est.m3u8",
    "group-title": "Kids"
  },
  "pbs_kids_2": {
    "name": "PBS Kids 2",
    "url": "https://2-fss-2.streamhoster.com/pl_140/amlst:200914-1298290/playlist.m3u8",
    "group-title": "Kids"
  },
  "racing_america": {
    "name": "Racing America",
    "url": "https://livetv-fa.tubi.video/racing-america/playlist.m3u8",
    "group-title": "Sports"
  },
  "ramogifmtv": {
    "name": "Ramogi Fm Tv",
    "url": "https://citizen.digital/tv/ramogi-fm-audio-visual-24",
    "logo": "https://viewtv-p2s3.onrender.com/uploads/ramogifm.png",
    "group-title": "News"
  },
  "ramogi-tv": {
    "name": "Ramogi Tv",
    "url": "https://citizen.digital/tv/ramogi-tv-19",
    "logo": "https://viewtv-p2s3.onrender.com/uploads/ramogi.png",
    "group-title": "News"
  },
  "ebru-tv": {
    "name": "Ebru Tv",
    "url": "https://kenyalivetv.co.ke/embed/ebru-tv-live",
    "logo": "https://viewtv-p2s3.onrender.com/uploads/ebru.png",
    "group-title": "News"
  },
  "kyeni-tv": {
    "name": "Kyeni Tv",
    "url": "https://vip.worldlivetv.stream/channel/KyeniTV_ke",
    "logo": "https://viewtv-p2s3.onrender.com/uploads/Kyeni.png",
    "group-title": "News"
  },
  "red_plus": {
    "name": "RED +",
    "url": "https://inforedvos.lcdn.claro.net.co/Content/HLS_HLS_DIR/Live/channel(REDMASHDWEB)/master.m3u8",
    "group-title": "Entertainment"
  },
  "tennis_channel": {
    "name": "Tennis Channel",
    "url": "https://cdn-ue1-prod.tsv2.amagi.tv/linear/amg01444-tennischannelth-tennischannelnl-samsungnl/playlist.m3u8",
    "group-title": "Sports"
  },
  "tiny_pop": {
    "name": "Tiny Pop",
    "url": "https://amg01753-narrativeuk-amg01753c1-lg-gb-1830.playouts.now.amagi.tv/playlist/amg01753-narrativeuk-tinypop-lggb/playlist.m3u8",
    "group-title": "Kids"
  },
  "tom-and-jerry": {
    "name": "Tom and Jerry",
    "url": "https://live20.bozztv.com/giatvplayout7/giatv-208314/playlist.m3u8",
    "group-title": "Kids"
  },
  "tv_mana_english": {
    "name": "Tv Mana [English]",
    "url": "https://w1.manasat.com/tvmana-english/smil:tvmana-english.smil/playlist.m3u8",
    "group-title": "Entertainment"
  },
  "twenty_four_hour_movies": {
    "name": "24 Hour Free Movie",
    "url": "https://d1j2u714xk898n.cloudfront.net/scheduler/scheduleMaster/145.m3u8",
    "group-title": "Movies"
  },
  "whole_world_tv": {
    "name": "Whole World Tv [Gospel]",
    "url": "https://mn-nl.mncdn.com/wholewordtv/wholewordtv/index.m3u8",
    "group-title": "Entertainment"
  },
  "zee_one": {
    "name": "Zee One",
    "url": "https://ef56ef401101403a8b06f1dec29ef1eb.mediatailor.us-east-1.amazonaws.com/v1/master/44f73ba4d03e9607dcd9bebdcb8494d86964f1d8/Samsung-de_ZeeOne/playlist.m3u8",
    "group-title": "Entertainment"
  },
  "hh": {
    "name": "1KZN TV",
    "url": "https://cdn.freevisiontv.co.za/sttv/smil:1kzn.stream.smil/playlist.m3u8",
    "logo": "https://admango.cdn.mangomolo.com/analytics/uploads/188/6544bebaae.jpg",
    "group-title": "Entertainment"
  },
  "yw": {
    "name": "Al Jazeera English",
    "url": "https://d1cy85syyhvqz5.cloudfront.net/v1/master/7b67fbda7ab859400a821e9aa0deda20ab7ca3d2/aljazeeraLive/AJE/index.m3u8",
    "logo": "https://i.imgur.com/7bRVpnu.png",
    "group-title": "News"
  },
  "ne": {
    "name": "Anytime TV",
    "url": "https://tv.anytimemedia.co.za:3673/hybrid/play.m3u8",
    "logo": "https://i.imgur.com/LloHzi4.png",
    "group-title": "Travel"
  },
  "qm": {
    "name": "BOKTV",
    "url": "https://livestream2.bokradio.co.za/hls/Bok5c.m3u8",
    "logo": "https://i.imgur.com/mcNjuuO.png",
    "group-title": "Music"
  },
  "bollywood": {
    "name": "Bollywood HD SD",
    "url": "https://d35j504z0x2vu2.cloudfront.net/v1/master/0bc8e8376bd8417a1b6761138aa41c26c7309312/bollywood-hd/manifest.m3u8",
    "logo": "https://i.imgur.com/scDKOLS.png",
    "group-title": "Movies"
  },
  "aa": {
    "name": "B+ TV",
    "url": "https://tv.btnrwanda.com:3432/live/bpluslive.m3u8",
    "logo": "https://i.ibb.co/WzLwj3X/IMG-20230703-155036.jpg",
    "group-title": "Entertainment"
  },
  "wwe": {
    "name": "Cable 14 Hamilton",
    "url": "https://flowcaster1-ch.cdn.clearcable.net/C14/smil:C14.smil/playlist.m3u8?iimae0UC2aendtime=1665196120&iimae0UC2ahash=NzcDbuotaJAVf1DsNxuGHBlfCXSvHDIt5sqMUMgrRMU=&iimae0UC2astarttime=1665181720",
    "logo": "https://i.imgur.com/bJ7ygTq.png",
    "group-title": ""
  },
  "jee": {
    "name": "CAtv",
    "url": "https://video2.getstreamhosting.com:19360/8216/8216.m3u8",
    "logo": "https://caribbeanadvantage.com/images/CAtv-logo-512.png",
    "group-title": "General"
  },
  "iu": {
    "name": "CBN Gospel",
    "url": "https://59d39900ebfb8.streamlock.net/ccbn/ccbn/playlist.m3u8",
    "logo": "https://i.imgur.com/SHBAblV.png",
    "group-title": "Religious"
  },
  "iop": {
    "name": "CBN TV",
    "url": "https://5790d294af2dc.streamlock.net/CBNVI/CBNVI/playlist.m3u8",
    "logo": "https://i.imgur.com/SHBAblV.png",
    "group-title": "General"
  },
  "yuh": {
    "name": "CeeJay TV",
    "url": "https://asiakwa.com/ceejaytv/index.fmp4.m3u8",
    "logo": "https://i.imgur.com/YgLMMOr.png",
    "group-title": "Entertainment"
  },
  "nh": {
    "name": "Channel 44",
    "url": "https://d1k6kax80wecy5.cloudfront.net/WFqZJc/index.m3u8",
    "logo": "https://i.imgur.com/P2wUGh9.png",
    "group-title": "General"
  },
  "ppo": {
    "name": "Channel 82 SD",
    "url": "https://service.webvideocore.net/CL1olYogIrDWvwqiIKK7eBmnWbRkKKsu3nqabm9GlX02JOj3CDNXzodJMDEN2dk3/a_bq9clxfbupwg.m3u8",
    "logo": "https://i.imgur.com/8Ff5b3e.png",
    "group-title": "Entertainment"
  },
  "qer": {
    "name": "Deluxe Dance",
    "url": "https://sdn-global-live-streaming-packager-cache.3qsdn.com/64733/64733_264_live.m3u8",
    "logo": "https://i.imgur.com/Qu7t15Y.png",
    "group-title": "Music"
  },
  "bbb": {
    "name": "Deluxe Rap",
    "url": "https://sdn-global-live-streaming-packager-cache.3qsdn.com/65183/65183_264_live.m3u8",
    "logo": "https://i.imgur.com/s3h67hx.png",
    "group-title": "Music"
  },
  "nd": {
    "name": "DW English",
    "url": "https://dwamdstream102.akamaized.net/hls/live/2015525/dwstream102/index.m3u8",
    "logo": "https://i.imgur.com/8MRNFb9.png",
    "group-title": "News"
  },
  "yyj": {
    "name": "EbS",
    "url": "https://streams.prd.commavservices.eu/live/ebs/index.m3u8",
    "logo": "https://i.imgur.com/DIIRPNN.png",
    "group-title": "Legislative"
  },
  "uojn": {
    "name": "EbS+",
    "url": "https://streams.prd.commavservices.eu/live/ebsplus/index.m3u8",
    "logo": "https://i.imgur.com/7V012zQ.png",
    "group-title": "Legislative"
  },
  "bsb": {
    "name": "Expo Channel",
    "url": "https://tvsnhlslivetest.akamaized.net/hls/live/2034711/EXPO-MSL4/master.m3u8",
    "logo": "https://i.imgur.com/2KzCShW.png",
    "group-title": "Shop"
  },
  "tyu": {
    "name": "FashionTV Europe",
    "url": "https://fashiontv-fashiontv-5-nl.samsung.wurl.tv/playlist.m3u8",
    "logo": "https://upload.wikimedia.org/wikipedia/commons/thumb/7/7a/Fashion_TV_logo.svg/512px-Fashion_TV_logo.svg.png",
    "group-title": "Lifestyle"
  },
  "fifa-a": {
    "name": "FIFA +",
    "url": "https://a62dad94.wurl.com/master/f36d25e7e52f1ba8d7e56eb859c636563214f541/UmFrdXRlblRWLWV1X0ZJRkFQbHVzRW5nbGlzaF9ITFM/playlist.m3u8",
    "logo": "https://i.imgur.com/l5iax42.png",
    "group-title": "Sports"
  },
  "yuig": {
    "name": "Firstlight",
    "url": "https://uni01rtmp.tulix.tv/firstlight/firstlight.smil/playlist.m3u8",
    "logo": "https://i.imgur.com/gtDROeT.png",
    "group-title": "Religious"
  },
  "jhu": {
    "name": "Fish TV",
    "url": "https://tv.localstreamgh.com/fishtv/index.m3u8",
    "logo": "https://i.imgur.com/A4VeRnS.png",
    "group-title": "General"
  },
  "uiipi": {
    "name": "For You TV",
    "url": "https://stream.az-multimedia.com:3793/live/foryoutvlive.m3u8",
    "logo": "https://i.imgur.com/1oMboXL.png",
    "group-title": "News"
  },
  "gsgs": {
    "name": "Fresh",
    "url": "https://origin3.afxp.telemedia.co.za/PremiumFree/freshtv/playlist.m3u8",
    "logo": "https://i.imgur.com/2ig8jUH.png",
    "group-title": "General"
  },
  "bsbs": {
    "name": "Hard Knocks Fighting Championship",
    "url": "https://d39g1vxj2ef6in.cloudfront.net/v1/manifest/3fec3e5cac39a52b2132f9c66c83dae043dc17d4/prod-rakuten-stitched/2ee2b8d4-acc4-4296-9dc8-66f1ffd0fff8/5.m3u8",
    "logo": "https://images-1.rakuten.tv/storage/global-live-channel/translation/artwork/13b0a6c7-4307-4c8d-9fc4-df2a4f8e8b38-hard-knocks-fighting-1602077398-width200-quality90.jpeg",
    "group-title": "General"
  },
  "enbs": {
    "name": "Kordia TV",
    "url": "https://ptvlive.kordia.net.nz/out/v1/3fc2254c865a457c8d7fbbce227a2aae/index.m3u8",
    "logo": "https://i.imgur.com/BQ0qWzX.png",
    "group-title": "General"
  },
  "ebhs": {
    "name": "Kozoom TV",
    "url": "https://streams2.sofast.tv/v1/master/611d79b11b77e2f571934fd80ca1413453772ac7/fdd6f243-f971-4a1a-9510-97ac01d6b37f/manifest.m3u8",
    "logo": "https://i.imgur.com/M1Ee79b.png",
    "group-title": "Sports"
  },
  "lolwe-tv": {
    "name": "Lolwe TV",
    "url": "https://goliveafrica.media:9998/live/62580e144eb43/index.m3u8",
    "logo": "https://viewtv-p2s3.onrender.com/uploads/lolwe.png",
    "group-title": "News"
  },
  "enhs": {
    "name": "My Righteous TV SD",
    "url": "https://live20.bozztv.com/ssh101/ssh101/myrighteous/playlist.m3u8",
    "logo": "https://i.imgur.com/wKSLNHB.png",
    "group-title": "Religious"
  },
  "seh": {
    "name": "NHK World-Japan SD",
    "url": "https://cdn4.skygo.mn/live/disk1/NHK_World/HLSv3-FTA/NHK_World.m3u8",
    "logo": "https://upload.wikimedia.org/wikipedia/commons/thumb/8/8d/NHK_World-Japan_TV.svg/512px-NHK_World-Japan_TV.svg.png",
    "group-title": "Culture"
  },
  "ywtw": {
    "name": "NRT Mexico Internacional",
    "url": "https://59e88b197fb16.streamlock.net:4443/live/canal24/playlist.m3u8",
    "logo": "https://i.imgur.com/W2E0fSy.png",
    "group-title": "News"
  },
  "bssb": {
    "name": "POP STAR",
    "url": "https://muzzik-live.morescreens.com/mts-3/playlist.m3u8",
    "logo": "https://i.imgur.com/E9ha9Or.png",
    "group-title": "Music"
  },
  "snbb": {
    "name": "Red Bull TV",
    "url": "https://3ea22335.wurl.com/master/f36d25e7e52f1ba8d7e56eb859c636563214f541/UmFrdXRlblRWLWdiX1JlZEJ1bGxUVl9ITFM/playlist.m3u8",
    "logo": "https://i.postimg.cc/8c78JM28/image.png",
    "group-title": "Sports"
  },
  "arena_sport_1_sd": {
    "name": "Arena Sport 1 SD",
    "url": "http://91.132.74.5:8000/play/a00k",
    "group-title": "Sports"
  },
  "campuslore": {
    "name": "CampusLore",
    "url": "https://linear-235.frequency.stream/dist/glewedtv/235/hls/master/playlist.m3u8",
    "group-title": "Lifestyle"
  },
  "canal_do_inter": {
    "name": "Canal do Inter",
    "url": "https://video01.soultv.com.br/internacional/internacional/playlist.m3u8",
    "group-title": "General"
  },
  "colimdo_tv": {
    "name": "Colimdo TV",
    "url": "https://cnn.livestreaminggroup.info:3132/live/colimdotvlive.m3u8",
    "group-title": "Entertainment"
  },
  "fight-network": {
    "name": "Fight Network",
    "url": "https://d12a2vxqkkh1bo.cloudfront.net/hls/main.m3u8",
    "group-title": "Sports"
  },
  "fuel_tv": {
    "name": "FUEL TV",
    "url": "https://amg01074-fueltv-amg01074c1-firetv-us-3150.playouts.now.amagi.tv/playlist.m3u8",
    "group-title": "Sports"
  },
  "game_plus": {
    "name": "Game+",
    "url": "https://a-cdn.klowdtv.com/live2/fntsy_720p/playlist.m3u8",
    "group-title": "Sports"
  },
  "gem_fit": {
    "name": "GEM Fit",
    "url": "https://ca-rt.onetv.app/gemfit/index-0.m3u8",
    "group-title": "Fashion"
  },
  "hard_knocks": {
    "name": "Hard Knocks",
    "url": "https://d3uyzhwvmemdyf.cloudfront.net/v1/master/9d062541f2ff39b5c0f48b743c6411d25f62fc25/Hard-Knocks-DistroTV/109.m3u8",
    "group-title": "General"
  },
  "k19": {
    "name": "K19",
    "url": "https://1853185335.rsc.cdn77.org/K192/tv/playlist.m3u8",
    "group-title": "General"
  },
  "ktv_sport": {
    "name": "KTV Sport",
    "url": "https://kwtspta.cdn.mangomolo.com/sp/smil:sp.stream.smil/chunklist.m3u8",
    "logo": "https://i.imgur.com/R1hGX1d.png",
    "group-title": "Sports"
  },
  "ktv_sport_plus": {
    "name": "KTV Sport Plus",
    "url": "https://kwtsplta.cdn.mangomolo.com/spl/smil:spl.stream.smil/chunklist.m3u8",
    "logo": "https://i.imgur.com/R1hGX1d.png",
    "group-title": "Sports"
  },
  "more_than_sports_tv": {
    "name": "More Than Sports TV",
    "url": "https://mts1.iptv-playoutcenter.de/mts/mts-web/playlist.m3u8",
    "logo": "https://i.imgur.com/hRNUo9n.png",
    "group-title": "Sports"
  },
  "racing-com": {
    "name": "Racing.com",
    "url": "https://racingvic-i.akamaized.net/hls/live/598695/racingvic/index1500.m3u8",
    "group-title": "Sports"
  },
  "red_bull_tv": {
    "name": "Red Bull TV",
    "url": "https://3ea22335.wurl.com/master/f36d25e7e52f1ba8d7e56eb859c636563214f541/UmFrdXRlblRWLWdiX1JlZEJ1bGxUVl9ITFM/playlist.m3u8",
    "logo": "https://i.imgur.com/7NeBmWX.jpg",
    "group-title": "Sports"
  },
  "rta_sport": {
    "name": "RTA Sport",
    "url": "https://rtatv.akamaized.net/Content/HLS/Live/channel(RTA3)/index.m3u8",
    "logo": "",
    "group-title": "Sports"
  },
  "sport_en_france": {
    "name": "Sport en France",
    "url": "https://sp1564435593.mytvchain.info/live/sp1564435593/index.m3u8",
    "logo": "https://upload.wikimedia.org/wikipedia/en/a/ad/Logo_of_French_sports_television_channel_Sport_en_France.png",
    "group-title": "Sports"
  },
  "ssc_action_waleed": {
    "name": "SSC Action Waleed",
    "url": "https://shls-live-event2-prod-dub.shahid.net/out/v1/0456ede1a39145d98b3d8c8062ddc998/index.m3u8",
    "group-title": "Movies"
  },
  "talksport": {
    "name": "talkSPORT",
    "url": "https://af7a8b4e.wurl.com/master/f36d25e7e52f1ba8d7e56eb859c636563214f541/TEctZ2JfdGFsa1NQT1JUX0hMUw/playlist.m3u8",
    "group-title": "Sports"
  },
  "trace_sport_stars": {
    "name": "Trace Sport Stars",
    "url": "https://trace-sportstars-samsungnz.amagi.tv/playlist.m3u8",
    "group-title": "Sports"
  },
  "tsn1": {
    "name": "TSN1",
    "url": "https://fl5.moveonjoy.com/TSN_1/index.m3u8",
    "group-title": "Sports"
  },
  "tsn2": {
    "name": "TSN2",
    "url": "https://fl5.moveonjoy.com/TSN_2/index.m3u8",
    "group-title": "Sports"
  },
  "tsn3": {
    "name": "TSN3",
    "url": "https://fl5.moveonjoy.com/TSN_3/index.m3u8",
    "group-title": "Sports"
  },
  "tsn4": {
    "name": "TSN4",
    "url": "https://fl5.moveonjoy.com/TSN_4/index.m3u8",
    "group-title": "Sports"
  },
  "tsn5": {
    "name": "TSN5",
    "url": "https://fl5.moveonjoy.com/TSN_5/index.m3u8",
    "group-title": "Sports"
  },
  "tsn_the_ocho_sd": {
    "name": "TSN The Ocho SD",
    "url": "https://d3pnbvng3bx2nj.cloudfront.net/v1/master/3722c60a815c199d9c0ef36c5b73da68a62b09d1/cc-rds8g35qfqrnv/TSN_The_Ocho.m3u8",
    "group-title": "General"
  },
  "t_sports_7": {
    "name": "T Sports 7",
    "url": "https://lb1-live-mv.v2h-cdn.com/hls/ffef/tsport/tsport.m3u8",
    "group-title": "Sports"
  },
  "cosmos_tv_sd": {
    "name": "Cosmos Tv",
    "url": "https://tv.mediacp.eu:19360/cosmos/cosmos.m3u8",
    "logo": "https://i0.wp.com/fmcosmos.com/wp-content/uploads/2021/11/COSMOS-TV.png",
    "group-title": "Movies"
  },
  "crave_2": {
    "name": "Crave 2",
    "url": "https://fl3.moveonjoy.com/CRAVE_2/index.m3u8",
    "logo": "https://i.imgur.com/e1qJ5Bp.png",
    "group-title": "Movies"
  },
  "crave_4": {
    "name": "Crave 4",
    "url": "https://fl3.moveonjoy.com/CRAVE_4/index.m3u8",
    "logo": "https://i.imgur.com/MyH3Q2p.png",
    "group-title": "Movies"
  },
  "abc_me_sydney": {
    "name": "ABC ME Sydney",
    "url": "https://c.mjh.nz/abc-me.m3u8",
    "logo": "https://i.imgur.com/6NyFLAm.png",
    "group-title": "Kids"
  },
  "etv_2": {
    "name": "ETV 2",
    "url": "https://sb.err.ee/live/etv2.m3u8",
    "logo": "https://i.imgur.com/fUjGHDa.png",
    "group-title": "Culture"
  },
  "ghost_tv": {
    "name": "Ghost TV",
    "url": "https://stmv.video.expressolider.com.br/ghostv/ghostv/playlist.m3u8",
    "logo": "https://i.imgur.com/ZVO8GVI.png",
    "group-title": "Movies"
  },
  "kika": {
    "name": "KiKA",
    "url": "https://kikageohls.akamaized.net/hls/live/2022693/livetvkika_de/master.m3u8",
    "logo": "https://i.imgur.com/vZdNp5S.png",
    "group-title": "Kids"
  },
  "mytime_movie_network": {
    "name": "MyTime Movie Network",
    "url": "https://appletree-mytime-samsungbrazil.amagi.tv/playlist.m3u8",
    "logo": "https://i.imgur.com/aiGQtzI.png",
    "group-title": "Movies"
  },
  "rai_movie": {
    "name": "Rai Movie",
    "url": "http://188.60.179.180:8000/play/xxRaiMOviexx",
    "logo": "https://i.imgur.com/0FjxXU9.png",
    "group-title": "Movies"
  },
  "smile_tv": {
    "name": "Smile TV",
    "url": "https://s1.cystream.net/live/smile/playlist.m3u8",
    "logo": "https://i.imgur.com/IAb4Gbf.png",
    "group-title": "Kids"
  },
  "tnt_kids_tv": {
    "name": "TNT Kids TV",
    "url": "https://restreamer1.tnt.ba/hls/tntkids.m3u8",
    "logo": "https://i.imgur.com/irTDbpn.png",
    "group-title": "Kids"
  },
  "thsdv": {
    "name": "Sky Open",
    "url": "https://tv.wyatts-server.com/stream/channelid/1977627680?auth=Lo47lPuhjUwYZIPv+NymH3qAyhMe1svINVM4Kac2fvA=&profile=pass",
    "logo": "https://i.imgur.com/eYyYojh.png",
    "group-title": "General"
  },
  "startv": {
    "name": "Star TV",
    "url": "http://62.233.57.226:8001/play/a008",
    "logo": "https://i.imgur.com/6BBnG6f.png",
    "group-title": "Entertainment"
  },
  "thsdvg": {
    "name": "TG4",
    "url": "https://dx4452e0qv6r9.cloudfront.net/tg4_vod_national.m3u8",
    "logo": "https://i.imgur.com/XiAKb4E.png",
    "group-title": "kids"
  },
  "yryegg": {
    "name": "TVM",
    "url": "http://80.79.6.221:25461/smash/public/19",
    "logo": "https://i.imgur.com/kpe0fYu.png",
    "group-title": "General"
  },
  "dnbd": {
    "name": "World Billiards",
    "url": "https://9a81dd4ee3884d0dbcacafaf0d81327a.mediatailor.us-east-1.amazonaws.com/v1/master/04fd913bb278d8775298c26fdca9d9841f37601f/RakutenTV-eu_BilliardsTV/playlist.m3u8",
    "logo": "https://images-3.rakuten.tv/storage/global-live-channel/translation/artwork/80af06f2-a12e-4406-bd13-b932fd69fffe-width200-quality90.png",
    "group-title": ""
  },
  "yeyeg": {
    "name": "World of Freesports SD",
    "url": "https://mainstreammedia-worldoffreesportsintl-rakuten.amagi.tv/hls/amagi_hls_data_rakutenAA-mainstreammediafreesportsintl-rakuten/CDN/master.m3u8",
    "logo": "https://images-1.rakuten.tv/storage/global-live-channel/translation/artwork/77aa6871-a13f-470b-a2d5-ca5650f63323-width200-quality90.jpeg",
    "group-title": "Sports"
  },
  "shhes": {
    "name": "Zee One",
    "url": "https://89ec2d15e090480bb419d940b8793b9c.mediatailor.us-east-1.amazonaws.com/v1/master/44f73ba4d03e9607dcd9bebdcb8494d86964f1d8/RakutenTV-eu_ZeeWorld-1/playlist.m3u8",
    "logo": "https://images-2.rakuten.tv/storage/global-live-channel/translation/artwork/b2b4d09d-3471-4dbf-a831-3191cfc66bec-width200-quality90.jpeg",
    "group-title": "Drama"
  },
  "bddh": {
    "name": "Z Nation",
    "url": "https://d39g1vxj2ef6in.cloudfront.net/v1/master/3fec3e5cac39a52b2132f9c66c83dae043dc17d4/prod-rakuten-stitched/master.m3u8?ads.xumo_channelId=88883098",
    "logo": "https://images-1.rakuten.tv/storage/global-live-channel/translation/artwork/dff3a92e-c4aa-49c4-b1b6-4a847428b8d5-width200-quality90.png",
    "group-title": "News"
  }
}